<?xml version="1.0" encoding="UTF-8" ?>
<!DOCTYPE mapper PUBLIC "-//mybatis.org//DTD Mapper 3.0//EN" "http://mybatis.org/dtd/mybatis-3-mapper.dtd" >
<mapper namespace="com.huyouxiao.space.dao.mapper.DepartmentEntityMapper" >
  <resultMap id="BaseResultMap" type="com.huyouxiao.space.dao.entity.DepartmentEntity" >
    <!--
      WARNING - @mbggenerated
      This element is automatically generated by MyBatis Generator, do not modify.
    -->
    <id column="id" property="id" jdbcType="BIGINT" />
    <result column="department_name" property="departmentName" jdbcType="VARCHAR" />
    <result column="area_id" property="areaId" jdbcType="BIGINT" />
    <result column="status" property="status" jdbcType="VARCHAR" />
  </resultMap>
  <sql id="Base_Column_List" >
    <!--
      WARNING - @mbggenerated
      This element is automatically generated by MyBatis Generator, do not modify.
    -->
    id, department_name, area_id, status
  </sql>
  <select id="selectByPrimaryKey" resultMap="BaseResultMap" parameterType="java.lang.Long" >
    <!--
      WARNING - @mbggenerated
      This element is automatically generated by MyBatis Generator, do not modify.
    -->
    select 
    <include refid="Base_Column_List" />
    from department
    where id = #{id,jdbcType=BIGINT}
  </select>
  <delete id="deleteByPrimaryKey" parameterType="java.lang.Long" >
    <!--
      WARNING - @mbggenerated
      This element is automatically generated by MyBatis Generator, do not modify.
    -->
    delete from department
    where id = #{id,jdbcType=BIGINT}
  </delete>
  <insert id="insert" parameterType="com.huyouxiao.space.dao.entity.DepartmentEntity" >
    <!--
      WARNING - @mbggenerated
      This element is automatically generated by MyBatis Generator, do not modify.
    -->
    insert into department (department_name, area_id, status
      )
    values (#{departmentName,jdbcType=VARCHAR}, #{areaId,jdbcType=BIGINT}, #{status,jdbcType=VARCHAR}
      )
    <selectKey resultType="java.lang.Long" keyProperty="id" >
      SELECT LAST_INSERT_ID()
    </selectKey>
  </insert>
  <insert id="insertSelective" parameterType="com.huyouxiao.space.dao.entity.DepartmentEntity" >
    <!--
      WARNING - @mbggenerated
      This element is automatically generated by MyBatis Generator, do not modify.
    -->
    insert into department
    <trim prefix="(" suffix=")" suffixOverrides="," >
      <if test="departmentName != null" >
        department_name,
      </if>
      <if test="areaId != null" >
        area_id,
      </if>
      <if test="status != null" >
        status,
      </if>
    </trim>
    <trim prefix="values (" suffix=")" suffixOverrides="," >
      <if test="departmentName != null" >
        #{departmentName,jdbcType=VARCHAR},
      </if>
      <if test="areaId != null" >
        #{areaId,jdbcType=BIGINT},
      </if>
      <if test="status != null" >
        #{status,jdbcType=VARCHAR},
      </if>
    </trim>
    <selectKey resultType="java.lang.Long" keyProperty="id" >
      SELECT LAST_INSERT_ID()
    </selectKey>
  </insert>
  <update id="updateByPrimaryKeySelective" parameterType="com.huyouxiao.space.dao.entity.DepartmentEntity" >
    <!--
      WARNING - @mbggenerated
      This element is automatically generated by MyBatis Generator, do not modify.
    -->
    update department
    <set >
      <if test="departmentName != null" >
        department_name = #{departmentName,jdbcType=VARCHAR},
      </if>
      <if test="areaId != null" >
        area_id = #{areaId,jdbcType=BIGINT},
      </if>
      <if test="status != null" >
        status = #{status,jdbcType=VARCHAR},
      </if>
    </set>
    where id = #{id,jdbcType=BIGINT}
  </update>
  <update id="updateByPrimaryKey" parameterType="com.huyouxiao.space.dao.entity.DepartmentEntity" >
    <!--
      WARNING - @mbggenerated
      This element is automatically generated by MyBatis Generator, do not modify.
    -->
    update department
    set department_name = #{departmentName,jdbcType=VARCHAR},
      area_id = #{areaId,jdbcType=BIGINT},
      status = #{status,jdbcType=VARCHAR}
    where id = #{id,jdbcType=BIGINT}
  </update>
</mapper>